light_curve-0.10.4.dist-info/RECORD
light_curve-0.10.4.dist-info/WHEEL
light_curve-0.10.4.dist-info/METADATA
light_curve/light_curve.abi3.so
light_curve/__init__.py
light_curve/light_curve_ext.py
light_curve/light_curve_py/minuit_lsq.py
light_curve/light_curve_py/warnings.py
light_curve/light_curve_py/minuit_ml.py
light_curve/light_curve_py/__init__.py
light_curve/light_curve_py/dataclass_field.py
light_curve/light_curve_py/features/stdev.py
light_curve/light_curve_py/features/_base.py
light_curve/light_curve_py/features/stetsonk.py
light_curve/light_curve_py/features/roms.py
light_curve/light_curve_py/features/redchi2.py
light_curve/light_curve_py/features/skew.py
light_curve/light_curve_py/features/cusum.py
light_curve/light_curve_py/features/flux_n_not_det_before_fd.py
light_curve/light_curve_py/features/excvar.py
light_curve/light_curve_py/features/amplitude.py
light_curve/light_curve_py/features/beyondnstd.py
light_curve/light_curve_py/features/__init__.py
light_curve/light_curve_py/features/weightmean.py
light_curve/light_curve_py/features/maxslope.py
light_curve/light_curve_py/features/extractor.py
light_curve/light_curve_py/features/mean.py
light_curve/light_curve_py/features/pdiffmperc.py
light_curve/light_curve_py/features/_lstsq.py
light_curve/light_curve_py/features/meanvar.py
light_curve/light_curve_py/features/etae.py
light_curve/light_curve_py/features/median.py
light_curve/light_curve_py/features/magnpratio.py
light_curve/light_curve_py/features/linfit.py
light_curve/light_curve_py/features/kurtosis.py
light_curve/light_curve_py/features/percampl.py
light_curve/light_curve_py/features/eta.py
light_curve/light_curve_py/features/medabsdev.py
light_curve/light_curve_py/features/_base_meta.py
light_curve/light_curve_py/features/lintrend.py
light_curve/light_curve_py/features/magnitude_n_not_det_before_fd.py
light_curve/light_curve_py/features/adnormal.py
light_curve/light_curve_py/features/color_of_median.py
light_curve/light_curve_py/features/ptp_var.py
light_curve/light_curve_py/features/otsusplit.py
