Metadata-Version: 2.4
Name: light-curve
Version: 0.10.4
Classifier: Intended Audience :: Science/Research
Classifier: License :: OSI Approved :: MIT License
Classifier: Programming Language :: Python
Classifier: Programming Language :: Python :: 3 :: Only
Classifier: Programming Language :: Python :: 3.9
Classifier: Programming Language :: Python :: 3.10
Classifier: Programming Language :: Python :: 3.11
Classifier: Programming Language :: Python :: 3.12
Classifier: Programming Language :: Python :: 3.13
Classifier: Programming Language :: Rust
Classifier: Topic :: Scientific/Engineering :: Astronomy
Requires-Dist: numpy
Requires-Dist: iminuit>=2.21,<3 ; extra == 'full'
Requires-Dist: scipy<2 ; extra == 'full'
Requires-Dist: pytest ; extra == 'test'
Requires-Dist: markdown-pytest ; extra == 'test'
Requires-Dist: pytest-benchmark ; extra == 'test'
Requires-Dist: pytest-subtests>=0.10 ; extra == 'test'
Requires-Dist: iminuit>=2.21,<3 ; extra == 'test'
Requires-Dist: numpy ; extra == 'test'
Requires-Dist: scipy ; extra == 'test'
Requires-Dist: cesium ; extra == 'test'
Requires-Dist: joblib ; extra == 'test'
Requires-Dist: pandas ; extra == 'test'
Requires-Dist: pytest ; extra == 'dev'
Requires-Dist: markdown-pytest ; extra == 'dev'
Requires-Dist: pytest-benchmark ; extra == 'dev'
Requires-Dist: pytest-subtests>=0.10 ; extra == 'dev'
Requires-Dist: iminuit>=2.21,<3 ; extra == 'dev'
Requires-Dist: numpy ; extra == 'dev'
Requires-Dist: scipy ; extra == 'dev'
Requires-Dist: cesium ; extra == 'dev'
Requires-Dist: joblib ; extra == 'dev'
Requires-Dist: pandas ; extra == 'dev'
Requires-Dist: black ; extra == 'dev'
Requires-Dist: ruff ; extra == 'dev'
Requires-Dist: pytest ; extra == 'dev-free-threading'
Requires-Dist: markdown-pytest ; extra == 'dev-free-threading'
Requires-Dist: pytest-benchmark ; extra == 'dev-free-threading'
Requires-Dist: pytest-subtests>=0.10 ; extra == 'dev-free-threading'
Requires-Dist: numpy ; extra == 'dev-free-threading'
Requires-Dist: scipy ; extra == 'dev-free-threading'
Requires-Dist: joblib ; extra == 'dev-free-threading'
Requires-Dist: pandas ; extra == 'dev-free-threading'
Requires-Dist: black ; extra == 'dev-free-threading'
Requires-Dist: ruff ; extra == 'dev-free-threading'
Provides-Extra: full
Provides-Extra: test
Provides-Extra: dev
Provides-Extra: dev-free-threading
Summary: Feature extractor from noisy time series
Author: Konstantin Malanchev <hombit@gmail.com>, Anastasia Lavrukhina <lavrukhina.ad@gmail.com>, Sergey Karpov, Etienne Russeil
Author-email: Konstantin Malanchev <hombit@gmail.com>, Anastasia Lavrukhina <lavrukhina.ad@gmail.com>, Sergey Karpov, Etienne Russeil
License: GPL-3.0-or-later
Requires-Python: >=3.9
Project-URL: Source Code, https://github.com/light-curve/light-curve-python
